exifMapOverlay/__init__.py
exifMapOverlay/__main__.py
exifMapOverlay/emo.py
exifMapOverlay/staticmap_cache.py
exifMapOverlay/resources/NotFound_emo.png
exifMapOverlay/resources/logo_emo.ico
exifmapoverlay-1.0.1.dist-info/licenses/LICENSE.txt
exifmapoverlay-1.0.1.dist-info/METADATA
exifmapoverlay-1.0.1.dist-info/WHEEL
exifmapoverlay-1.0.1.dist-info/top_level.txt
exifmapoverlay-1.0.1.dist-info/RECORD
