Metadata-Version: 2.4
Name: exifMapOverlay
Version: 1.0.1
Summary: A little tool to show a simple window with a map based on exif gps location.
Author-email: sayofan <sayofan+exifMapOverlay@proton.me>
License-Expression: Apache-2.0
Project-URL: Homepage, https://github.com/sayofan/ExifMapOverlay
Keywords: images,openstreetmap,osm,geolocation
Classifier: Programming Language :: Python :: 3
Classifier: Operating System :: OS Independent
Classifier: Intended Audience :: End Users/Desktop
Classifier: Topic :: Multimedia :: Graphics :: Viewers
Requires-Python: >=3.9
License-File: LICENSE.txt
Requires-Dist: OSMPythonTools>=0.3.3
Requires-Dist: Pillow
Requires-Dist: requests
Provides-Extra: installer
Requires-Dist: PyInstaller; extra == "installer"
Dynamic: license-file
